{
  "author": "Microsoft",
  "name": "Aplikace .NET MAUI Blazor Hybrid",
  "description": "Projekt pro vytvoření .NET MAUI aplikace pro iOS, Android, Mac Catalyst a WinUI pomocí Blazor Hybrid",
  "postActions/openInEditor/description": "Otevře v editoru Components/Pages/Home.razor.",
  "symbols/applicationId/description": "Přepíše v projektu $(ApplicationId)",
  "symbols/Framework/description": "Cílová architektura pro projekt.",
  "symbols/Framework/choices/DOTNET_TFM_VALUE/description": "Cílový DOTNET_TFM_VALUE",
  "symbols/IncludeSampleContent/displayName": "_Zahrnout ukázkové stránky",
  "symbols/IncludeSampleContent/description": "Nastavuje, jestli se mají přidávat ukázkové stránky a styly pro demonstraci základních vzorů použití.",
  "symbols/Empty/description": "Nastavuje, jestli se mají vynechat ukázkové stránky a styly, které demonstrují základní vzory použití."
}