<Dependencies>
  <ProductDependencies>
    <Dependency Name="Microsoft.Dotnet.Sdk.Internal" Version="8.0.100-rc.1.23409.22" CoherentParentDependency="Microsoft.Android.Sdk.Windows">
      <Uri>https://github.com/dotnet/installer</Uri>
      <Sha>27b2889484e8cd8f39b608e0803e5c2a6a4a8fd7</Sha>
    </Dependency>
    <Dependency Name="Microsoft.NETCore.App.Ref" Version="8.0.0-rc.1.23381.3" CoherentParentDependency="Microsoft.Android.Sdk.Windows">
      <Uri>https://github.com/dotnet/runtime</Uri>
      <Sha>e71faeeeccba29c1f06c7020929cfdadbd32401e</Sha>
    </Dependency>
    <Dependency Name="Microsoft.Android.Sdk.Windows" Version="34.0.0-rc.1.418">
      <Uri>https://github.com/xamarin/xamarin-android</Uri>
      <Sha>da980071815ea2572223112f77bfd257115ceb97</Sha>
    </Dependency>
    <Dependency Name="Microsoft.MacCatalyst.Sdk" Version="16.4.8741-net8-rc1">
      <Uri>https://github.com/xamarin/xamarin-macios</Uri>
      <Sha>0c602c1f8878ed6c561c9ce0844857e996b060ab</Sha>
    </Dependency>
    <Dependency Name="Microsoft.macOS.Sdk" Version="13.3.8741-net8-rc1">
      <Uri>https://github.com/xamarin/xamarin-macios</Uri>
      <Sha>0c602c1f8878ed6c561c9ce0844857e996b060ab</Sha>
    </Dependency>
    <Dependency Name="Microsoft.iOS.Sdk" Version="16.4.8741-net8-rc1">
      <Uri>https://github.com/xamarin/xamarin-macios</Uri>
      <Sha>0c602c1f8878ed6c561c9ce0844857e996b060ab</Sha>
    </Dependency>
    <Dependency Name="Microsoft.tvOS.Sdk" Version="16.4.8741-net8-rc1">
      <Uri>https://github.com/xamarin/xamarin-macios</Uri>
      <Sha>0c602c1f8878ed6c561c9ce0844857e996b060ab</Sha>
    </Dependency>
    <Dependency Name="Microsoft.NET.Workload.Emscripten.Current.Manifest-8.0.100.Transport" Version="8.0.0-rc.1.23377.1" CoherentParentDependency="Microsoft.NETCore.App.Ref">
      <Uri>https://github.com/dotnet/emsdk</Uri>
      <Sha>3a52d07cd6a500d81d9cee79cbc8f0b9a90e1dbf</Sha>
    </Dependency>
    <Dependency Name="Microsoft.WindowsAppSDK" Version="0.0.1">
      <Uri>https://dev.azure.com/microsoft/ProjectReunion/_git/ProjectReunionInternal</Uri>
    </Dependency>
    <Dependency Name="Microsoft.AspNetCore.Authorization" Version="8.0.0-preview.7.23364.32">
      <Uri>https://github.com/dotnet/aspnetcore</Uri>
      <Sha>240377059ec25b4d9d86d4188a26722e55edc5a1</Sha>
    </Dependency>
    <Dependency Name="Microsoft.AspNetCore.Authentication.Facebook" Version="8.0.0-preview.7.23364.32">
      <Uri>https://github.com/dotnet/aspnetcore</Uri>
      <Sha>240377059ec25b4d9d86d4188a26722e55edc5a1</Sha>
    </Dependency>
    <Dependency Name="Microsoft.AspNetCore.Authentication.Google" Version="8.0.0-preview.7.23364.32">
      <Uri>https://github.com/dotnet/aspnetcore</Uri>
      <Sha>240377059ec25b4d9d86d4188a26722e55edc5a1</Sha>
    </Dependency>
    <Dependency Name="Microsoft.AspNetCore.Authentication.MicrosoftAccount" Version="8.0.0-preview.7.23364.32">
      <Uri>https://github.com/dotnet/aspnetcore</Uri>
      <Sha>240377059ec25b4d9d86d4188a26722e55edc5a1</Sha>
    </Dependency>
    <Dependency Name="Microsoft.AspNetCore.Components" Version="8.0.0-preview.7.23364.32">
      <Uri>https://github.com/dotnet/aspnetcore</Uri>
      <Sha>240377059ec25b4d9d86d4188a26722e55edc5a1</Sha>
    </Dependency>
    <Dependency Name="Microsoft.AspNetCore.Components.Analyzers" Version="8.0.0-preview.7.23364.32">
      <Uri>https://github.com/dotnet/aspnetcore</Uri>
      <Sha>240377059ec25b4d9d86d4188a26722e55edc5a1</Sha>
    </Dependency>
    <Dependency Name="Microsoft.AspNetCore.Components.Forms" Version="8.0.0-preview.7.23364.32">
      <Uri>https://github.com/dotnet/aspnetcore</Uri>
      <Sha>240377059ec25b4d9d86d4188a26722e55edc5a1</Sha>
    </Dependency>
    <Dependency Name="Microsoft.AspNetCore.Components.WebView" Version="8.0.0-preview.7.23364.32">
      <Uri>https://github.com/dotnet/aspnetcore</Uri>
      <Sha>240377059ec25b4d9d86d4188a26722e55edc5a1</Sha>
    </Dependency>
    <Dependency Name="Microsoft.AspNetCore.Components.Web" Version="8.0.0-preview.7.23364.32">
      <Uri>https://github.com/dotnet/aspnetcore</Uri>
      <Sha>240377059ec25b4d9d86d4188a26722e55edc5a1</Sha>
    </Dependency>
    <Dependency Name="Microsoft.AspNetCore.Metadata" Version="8.0.0-preview.7.23364.32">
      <Uri>https://github.com/dotnet/aspnetcore</Uri>
      <Sha>240377059ec25b4d9d86d4188a26722e55edc5a1</Sha>
    </Dependency>
    <Dependency Name="Microsoft.JSInterop" Version="8.0.0-preview.7.23364.32">
      <Uri>https://github.com/dotnet/aspnetcore</Uri>
      <Sha>240377059ec25b4d9d86d4188a26722e55edc5a1</Sha>
    </Dependency>
    <Dependency Name="Microsoft.TemplateEngine.Tasks" Version="7.0.100-preview.2.22102.8">
      <Uri>https://github.com/dotnet/templating</Uri>
      <Sha>3f4da9ced34942d83054e647f3b1d9d7dde281e8</Sha>
    </Dependency>
    <Dependency Name="Microsoft.DotNet.XHarness.TestRunners.Common" Version="8.0.0-prerelease.23407.2">
      <Uri>https://github.com/dotnet/xharness</Uri>
      <Sha>480b9159eb7e69b182a87581d5a336e97e0b6dae</Sha>
    </Dependency>
    <Dependency Name="Microsoft.DotNet.XHarness.TestRunners.Xunit" Version="8.0.0-prerelease.23407.2">
      <Uri>https://github.com/dotnet/xharness</Uri>
      <Sha>480b9159eb7e69b182a87581d5a336e97e0b6dae</Sha>
    </Dependency>
    <Dependency Name="Microsoft.DotNet.XHarness.CLI" Version="8.0.0-prerelease.23407.2">
      <Uri>https://github.com/dotnet/xharness</Uri>
      <Sha>480b9159eb7e69b182a87581d5a336e97e0b6dae</Sha>
    </Dependency>
  </ProductDependencies>
</Dependencies>
