<Dependencies>
  <ProductDependencies>
    <Dependency Name="Microsoft.NET.Sdk" Version="9.0.100-rtm.24502.1">
      <Uri>https://github.com/dotnet/sdk</Uri>
      <Sha>646e1d91cf045935f41ebd0a31e77201f5a7353f</Sha>
    </Dependency>
    <Dependency Name="Microsoft.NETCore.App.Ref" Version="9.0.0-rtm.24476.4" CoherentParentDependency="Microsoft.NET.Sdk">
      <Uri>https://github.com/dotnet/runtime</Uri>
      <Sha>0d44aea3696bab80b11a12c6bdfdbf8de9c4e815</Sha>
    </Dependency>
    <Dependency Name="Microsoft.Android.Sdk.Windows" Version="35.0.1-ci.main.17">
      <Uri>https://github.com/dotnet/android</Uri>
      <Sha>5f58b76a63c7af9bf3046a48e1ba34cdcd33797f</Sha>
    </Dependency>
    <Dependency Name="Microsoft.MacCatalyst.Sdk.net9.0_18.0" Version="18.0.9565-net9-rc2">
      <Uri>https://github.com/xamarin/xamarin-macios</Uri>
      <Sha>22b5933ebb490b90f1ec13da4aa6b3c222f09e27</Sha>
    </Dependency>
    <Dependency Name="Microsoft.macOS.Sdk.net9.0_15.0" Version="15.0.9565-net9-rc2">
      <Uri>https://github.com/xamarin/xamarin-macios</Uri>
      <Sha>22b5933ebb490b90f1ec13da4aa6b3c222f09e27</Sha>
    </Dependency>
    <Dependency Name="Microsoft.iOS.Sdk.net9.0_18.0" Version="18.0.9565-net9-rc2">
      <Uri>https://github.com/xamarin/xamarin-macios</Uri>
      <Sha>22b5933ebb490b90f1ec13da4aa6b3c222f09e27</Sha>
    </Dependency>
    <Dependency Name="Microsoft.tvOS.Sdk.net9.0_18.0" Version="18.0.9565-net9-rc2">
      <Uri>https://github.com/xamarin/xamarin-macios</Uri>
      <Sha>22b5933ebb490b90f1ec13da4aa6b3c222f09e27</Sha>
    </Dependency>
    <Dependency Name="Microsoft.WindowsAppSDK" Version="0.0.1">
      <Uri>https://dev.azure.com/microsoft/ProjectReunion/_git/ProjectReunionInternal</Uri>
    </Dependency>
    <Dependency Name="Microsoft.NET.Workload.Emscripten.Current.Manifest-9.0.100.Transport" Version="9.0.0-rtm.24469.1" CoherentParentDependency="Microsoft.NETCore.App.Ref">
      <Uri>https://github.com/dotnet/emsdk</Uri>
      <Sha>8e660ff41e91879977e3a9d837e068bd72234c26</Sha>
    </Dependency>
    <Dependency Name="Microsoft.AspNetCore.Authorization" Version="9.0.0-rtm.24501.7">
      <Uri>https://github.com/dotnet/aspnetcore</Uri>
      <Sha>9d5458536b0e28996570b0ebbb1c2dbc5afedf56</Sha>
    </Dependency>
    <Dependency Name="Microsoft.AspNetCore.Authentication.Facebook" Version="9.0.0-rtm.24501.7">
      <Uri>https://github.com/dotnet/aspnetcore</Uri>
      <Sha>9d5458536b0e28996570b0ebbb1c2dbc5afedf56</Sha>
    </Dependency>
    <Dependency Name="Microsoft.AspNetCore.Authentication.Google" Version="9.0.0-rtm.24501.7">
      <Uri>https://github.com/dotnet/aspnetcore</Uri>
      <Sha>9d5458536b0e28996570b0ebbb1c2dbc5afedf56</Sha>
    </Dependency>
    <Dependency Name="Microsoft.AspNetCore.Authentication.MicrosoftAccount" Version="9.0.0-rtm.24501.7">
      <Uri>https://github.com/dotnet/aspnetcore</Uri>
      <Sha>9d5458536b0e28996570b0ebbb1c2dbc5afedf56</Sha>
    </Dependency>
    <Dependency Name="Microsoft.AspNetCore.Components" Version="9.0.0-rtm.24501.7">
      <Uri>https://github.com/dotnet/aspnetcore</Uri>
      <Sha>9d5458536b0e28996570b0ebbb1c2dbc5afedf56</Sha>
    </Dependency>
    <Dependency Name="Microsoft.AspNetCore.Components.Analyzers" Version="9.0.0-rtm.24501.7">
      <Uri>https://github.com/dotnet/aspnetcore</Uri>
      <Sha>9d5458536b0e28996570b0ebbb1c2dbc5afedf56</Sha>
    </Dependency>
    <Dependency Name="Microsoft.AspNetCore.Components.Forms" Version="9.0.0-rtm.24501.7">
      <Uri>https://github.com/dotnet/aspnetcore</Uri>
      <Sha>9d5458536b0e28996570b0ebbb1c2dbc5afedf56</Sha>
    </Dependency>
    <Dependency Name="Microsoft.AspNetCore.Components.WebAssembly" Version="9.0.0-rtm.24501.7">
      <Uri>https://github.com/dotnet/aspnetcore</Uri>
      <Sha>9d5458536b0e28996570b0ebbb1c2dbc5afedf56</Sha>
    </Dependency>
    <Dependency Name="Microsoft.AspNetCore.Components.WebAssembly.Server" Version="9.0.0-rtm.24501.7">
      <Uri>https://github.com/dotnet/aspnetcore</Uri>
      <Sha>9d5458536b0e28996570b0ebbb1c2dbc5afedf56</Sha>
    </Dependency>
    <Dependency Name="Microsoft.AspNetCore.Components.WebView" Version="9.0.0-rtm.24501.7">
      <Uri>https://github.com/dotnet/aspnetcore</Uri>
      <Sha>9d5458536b0e28996570b0ebbb1c2dbc5afedf56</Sha>
    </Dependency>
    <Dependency Name="Microsoft.AspNetCore.Components.Web" Version="9.0.0-rtm.24501.7">
      <Uri>https://github.com/dotnet/aspnetcore</Uri>
      <Sha>9d5458536b0e28996570b0ebbb1c2dbc5afedf56</Sha>
    </Dependency>
    <Dependency Name="Microsoft.AspNetCore.Metadata" Version="9.0.0-rtm.24501.7">
      <Uri>https://github.com/dotnet/aspnetcore</Uri>
      <Sha>9d5458536b0e28996570b0ebbb1c2dbc5afedf56</Sha>
    </Dependency>
    <Dependency Name="Microsoft.JSInterop" Version="9.0.0-rtm.24501.7">
      <Uri>https://github.com/dotnet/aspnetcore</Uri>
      <Sha>9d5458536b0e28996570b0ebbb1c2dbc5afedf56</Sha>
    </Dependency>
    <Dependency Name="Microsoft.TemplateEngine.Tasks" Version="7.0.100-preview.2.22102.8">
      <Uri>https://github.com/dotnet/templating</Uri>
      <Sha>3f4da9ced34942d83054e647f3b1d9d7dde281e8</Sha>
    </Dependency>
    <Dependency Name="Microsoft.Extensions.Configuration" Version="9.0.0-rtm.24476.4" CoherentParentDependency="Microsoft.AspNetCore.Authorization">
      <Uri>https://github.com/dotnet/runtime</Uri>
      <Sha>0d44aea3696bab80b11a12c6bdfdbf8de9c4e815</Sha>
    </Dependency>
    <Dependency Name="Microsoft.Extensions.Configuration.Abstractions" Version="9.0.0-rtm.24476.4" CoherentParentDependency="Microsoft.AspNetCore.Authorization">
      <Uri>https://github.com/dotnet/runtime</Uri>
      <Sha>0d44aea3696bab80b11a12c6bdfdbf8de9c4e815</Sha>
    </Dependency>
    <Dependency Name="Microsoft.Extensions.Configuration.Json" Version="9.0.0-rtm.24476.4" CoherentParentDependency="Microsoft.AspNetCore.Authorization">
      <Uri>https://github.com/dotnet/runtime</Uri>
      <Sha>0d44aea3696bab80b11a12c6bdfdbf8de9c4e815</Sha>
    </Dependency>
    <Dependency Name="Microsoft.Extensions.DependencyInjection" Version="9.0.0-rtm.24476.4" CoherentParentDependency="Microsoft.AspNetCore.Authorization">
      <Uri>https://github.com/dotnet/runtime</Uri>
      <Sha>0d44aea3696bab80b11a12c6bdfdbf8de9c4e815</Sha>
    </Dependency>
    <Dependency Name="Microsoft.Extensions.DependencyInjection.Abstractions" Version="9.0.0-rtm.24476.4" CoherentParentDependency="Microsoft.AspNetCore.Authorization">
      <Uri>https://github.com/dotnet/runtime</Uri>
      <Sha>0d44aea3696bab80b11a12c6bdfdbf8de9c4e815</Sha>
    </Dependency>
    <Dependency Name="Microsoft.Extensions.FileProviders.Abstractions" Version="9.0.0-rtm.24476.4" CoherentParentDependency="Microsoft.AspNetCore.Authorization">
      <Uri>https://github.com/dotnet/runtime</Uri>
      <Sha>0d44aea3696bab80b11a12c6bdfdbf8de9c4e815</Sha>
    </Dependency>
    <Dependency Name="Microsoft.Extensions.Logging.Abstractions" Version="9.0.0-rtm.24476.4" CoherentParentDependency="Microsoft.AspNetCore.Authorization">
      <Uri>https://github.com/dotnet/runtime</Uri>
      <Sha>0d44aea3696bab80b11a12c6bdfdbf8de9c4e815</Sha>
    </Dependency>
    <Dependency Name="Microsoft.Extensions.Logging" Version="9.0.0-rtm.24476.4" CoherentParentDependency="Microsoft.AspNetCore.Authorization">
      <Uri>https://github.com/dotnet/runtime</Uri>
      <Sha>0d44aea3696bab80b11a12c6bdfdbf8de9c4e815</Sha>
    </Dependency>
    <Dependency Name="Microsoft.Extensions.Logging.Console" Version="9.0.0-rtm.24476.4" CoherentParentDependency="Microsoft.AspNetCore.Authorization">
      <Uri>https://github.com/dotnet/runtime</Uri>
      <Sha>0d44aea3696bab80b11a12c6bdfdbf8de9c4e815</Sha>
    </Dependency>
    <Dependency Name="Microsoft.Extensions.Logging.Debug" Version="9.0.0-rtm.24476.4" CoherentParentDependency="Microsoft.AspNetCore.Authorization">
      <Uri>https://github.com/dotnet/runtime</Uri>
      <Sha>0d44aea3696bab80b11a12c6bdfdbf8de9c4e815</Sha>
    </Dependency>
    <Dependency Name="Microsoft.Extensions.Primitives" Version="9.0.0-rtm.24476.4" CoherentParentDependency="Microsoft.AspNetCore.Authorization">
      <Uri>https://github.com/dotnet/runtime</Uri>
      <Sha>0d44aea3696bab80b11a12c6bdfdbf8de9c4e815</Sha>
    </Dependency>
    <Dependency Name="Microsoft.DotNet.XHarness.TestRunners.Common" Version="10.0.0-prerelease.24501.1">
      <Uri>https://github.com/dotnet/xharness</Uri>
      <Sha>2b6293f14cf55326dde74b1364d12c579a8bd569</Sha>
    </Dependency>
    <Dependency Name="Microsoft.DotNet.XHarness.TestRunners.Xunit" Version="10.0.0-prerelease.24501.1">
      <Uri>https://github.com/dotnet/xharness</Uri>
      <Sha>2b6293f14cf55326dde74b1364d12c579a8bd569</Sha>
    </Dependency>
    <Dependency Name="Microsoft.DotNet.XHarness.CLI" Version="10.0.0-prerelease.24501.1">
      <Uri>https://github.com/dotnet/xharness</Uri>
      <Sha>2b6293f14cf55326dde74b1364d12c579a8bd569</Sha>
    </Dependency>
  </ProductDependencies>
  <ToolsetDependencies>
    <Dependency Name="Microsoft.DotNet.Build.Tasks.Feed" Version="10.0.0-beta.24503.1">
      <Uri>https://github.com/dotnet/arcade</Uri>
      <Sha>36084e26cde6e5902e0d7ada5b097efd79835682</Sha>
    </Dependency>
    <Dependency Name="Microsoft.DotNet.Arcade.Sdk" Version="10.0.0-beta.24503.1">
      <Uri>https://github.com/dotnet/arcade</Uri>
      <Sha>36084e26cde6e5902e0d7ada5b097efd79835682</Sha>
      <SourceBuild RepoName="arcade" ManagedOnly="true" />
    </Dependency>
  </ToolsetDependencies>
</Dependencies>
